{
  "requested_domain": "educart.co",
  "matched_domain": "educart.co",
  "release": "cc-main-2026-jan-feb-mar",
  "generated_on": "2026-04-21T13:48:18.868Z",
  "no_match": false,
  "backlinks": [
    {
      "linking_domain": "indianonlineseller.com",
      "host_count": "7396",
      "edge_count": "1"
    },
    {
      "linking_domain": "gotrackier.com",
      "host_count": "137",
      "edge_count": "1"
    },
    {
      "linking_domain": "feedspot.com",
      "host_count": "123",
      "edge_count": "1"
    },
    {
      "linking_domain": "hindustantimes.com",
      "host_count": "81",
      "edge_count": "1"
    },
    {
      "linking_domain": "kvs.gov.in",
      "host_count": "51",
      "edge_count": "1"
    },
    {
      "linking_domain": "thrinacia.com",
      "host_count": "30",
      "edge_count": "1"
    },
    {
      "linking_domain": "twinspires.com",
      "host_count": "30",
      "edge_count": "1"
    },
    {
      "linking_domain": "norml.org",
      "host_count": "23",
      "edge_count": "1"
    },
    {
      "linking_domain": "expose-news.com",
      "host_count": "11",
      "edge_count": "1"
    },
    {
      "linking_domain": "flash.co",
      "host_count": "7",
      "edge_count": "1"
    },
    {
      "linking_domain": "fastread.in",
      "host_count": "5",
      "edge_count": "1"
    },
    {
      "linking_domain": "freightbrokerbootcamp.com",
      "host_count": "5",
      "edge_count": "1"
    },
    {
      "linking_domain": "thesocietypages.org",
      "host_count": "5",
      "edge_count": "1"
    },
    {
      "linking_domain": "turboseotools.com",
      "host_count": "4",
      "edge_count": "1"
    },
    {
      "linking_domain": "kanilprwire.com",
      "host_count": "3",
      "edge_count": "1"
    },
    {
      "linking_domain": "menagerie.media",
      "host_count": "3",
      "edge_count": "1"
    },
    {
      "linking_domain": "aajtakknews.com",
      "host_count": "2",
      "edge_count": "1"
    },
    {
      "linking_domain": "agpgroup.in",
      "host_count": "2",
      "edge_count": "1"
    },
    {
      "linking_domain": "allforbloggers.com",
      "host_count": "2",
      "edge_count": "1"
    },
    {
      "linking_domain": "blogsplusplus.com",
      "host_count": "2",
      "edge_count": "1"
    },
    {
      "linking_domain": "coolztricks.com",
      "host_count": "2",
      "edge_count": "1"
    },
    {
      "linking_domain": "dearbloggers.com",
      "host_count": "2",
      "edge_count": "1"
    },
    {
      "linking_domain": "espressoadventures.com",
      "host_count": "2",
      "edge_count": "1"
    },
    {
      "linking_domain": "growingwithnemit.com",
      "host_count": "2",
      "edge_count": "1"
    },
    {
      "linking_domain": "houstonstevenson.com",
      "host_count": "2",
      "edge_count": "1"
    },
    {
      "linking_domain": "iotkoreamall.com",
      "host_count": "2",
      "edge_count": "1"
    },
    {
      "linking_domain": "lesarkarijobs.com",
      "host_count": "2",
      "edge_count": "1"
    },
    {
      "linking_domain": "recomind.net",
      "host_count": "2",
      "edge_count": "1"
    },
    {
      "linking_domain": "studiopress.community",
      "host_count": "2",
      "edge_count": "1"
    },
    {
      "linking_domain": "theedupartner.com",
      "host_count": "2",
      "edge_count": "1"
    },
    {
      "linking_domain": "thermalpowertech.com",
      "host_count": "2",
      "edge_count": "1"
    },
    {
      "linking_domain": "trickzon.com",
      "host_count": "2",
      "edge_count": "1"
    },
    {
      "linking_domain": "wap5.in",
      "host_count": "2",
      "edge_count": "1"
    },
    {
      "linking_domain": "wootfi.com",
      "host_count": "2",
      "edge_count": "1"
    },
    {
      "linking_domain": "allmedia.ae",
      "host_count": "1",
      "edge_count": "1"
    },
    {
      "linking_domain": "blacksocially.com",
      "host_count": "1",
      "edge_count": "1"
    },
    {
      "linking_domain": "citytime.co.in",
      "host_count": "1",
      "edge_count": "1"
    },
    {
      "linking_domain": "colored.club",
      "host_count": "1",
      "edge_count": "1"
    },
    {
      "linking_domain": "culturesbook.com",
      "host_count": "1",
      "edge_count": "1"
    },
    {
      "linking_domain": "dmcinsider.com",
      "host_count": "1",
      "edge_count": "1"
    },
    {
      "linking_domain": "getbacklinks.com.au",
      "host_count": "1",
      "edge_count": "1"
    },
    {
      "linking_domain": "integratedblogs.com",
      "host_count": "1",
      "edge_count": "1"
    },
    {
      "linking_domain": "ladderpython.com",
      "host_count": "1",
      "edge_count": "1"
    },
    {
      "linking_domain": "locantotech.com",
      "host_count": "1",
      "edge_count": "1"
    },
    {
      "linking_domain": "ncips.in",
      "host_count": "1",
      "edge_count": "1"
    },
    {
      "linking_domain": "snupto.com",
      "host_count": "1",
      "edge_count": "1"
    },
    {
      "linking_domain": "trendingblogsweb.com",
      "host_count": "1",
      "edge_count": "1"
    },
    {
      "linking_domain": "witenrepreneur.com",
      "host_count": "1",
      "edge_count": "1"
    }
  ]
}
