{
  "requested_domain": "learninsta.com",
  "matched_domain": "learninsta.com",
  "release": "cc-main-2026-jan-feb-mar",
  "generated_on": "2026-04-21T07:05:09.863Z",
  "no_match": false,
  "backlinks": [
    {
      "linking_domain": "vercel.app",
      "host_count": "106085",
      "edge_count": "1"
    },
    {
      "linking_domain": "netlify.app",
      "host_count": "80644",
      "edge_count": "1"
    },
    {
      "linking_domain": "careers360.com",
      "host_count": "46",
      "edge_count": "1"
    },
    {
      "linking_domain": "norml.org",
      "host_count": "23",
      "edge_count": "1"
    },
    {
      "linking_domain": "edugrown.in",
      "host_count": "11",
      "edge_count": "1"
    },
    {
      "linking_domain": "studyrate.in",
      "host_count": "5",
      "edge_count": "1"
    },
    {
      "linking_domain": "learncbse.in",
      "host_count": "4",
      "edge_count": "1"
    },
    {
      "linking_domain": "ribblu.com",
      "host_count": "4",
      "edge_count": "1"
    },
    {
      "linking_domain": "truemaths.com",
      "host_count": "4",
      "edge_count": "1"
    },
    {
      "linking_domain": "aplustopper.com",
      "host_count": "3",
      "edge_count": "1"
    },
    {
      "linking_domain": "esad.edu.br",
      "host_count": "3",
      "edge_count": "1"
    },
    {
      "linking_domain": "ncerttextbook.in",
      "host_count": "3",
      "edge_count": "1"
    },
    {
      "linking_domain": "amaraxom.com",
      "host_count": "2",
      "edge_count": "1"
    },
    {
      "linking_domain": "amreshacademy.in",
      "host_count": "2",
      "edge_count": "1"
    },
    {
      "linking_domain": "bhavyeducation.com",
      "host_count": "2",
      "edge_count": "1"
    },
    {
      "linking_domain": "cbsesamplepapers.info",
      "host_count": "2",
      "edge_count": "1"
    },
    {
      "linking_domain": "cbsetips.in",
      "host_count": "2",
      "edge_count": "1"
    },
    {
      "linking_domain": "creativeflight.in",
      "host_count": "2",
      "edge_count": "1"
    },
    {
      "linking_domain": "eastwestnewsservice.com",
      "host_count": "2",
      "edge_count": "1"
    },
    {
      "linking_domain": "englishfun.in",
      "host_count": "2",
      "edge_count": "1"
    },
    {
      "linking_domain": "hsslive.guru",
      "host_count": "2",
      "edge_count": "1"
    },
    {
      "linking_domain": "iotkoreamall.com",
      "host_count": "2",
      "edge_count": "1"
    },
    {
      "linking_domain": "keralanotes.com",
      "host_count": "2",
      "edge_count": "1"
    },
    {
      "linking_domain": "kseebsolutions.com",
      "host_count": "2",
      "edge_count": "1"
    },
    {
      "linking_domain": "learncram.com",
      "host_count": "2",
      "edge_count": "1"
    },
    {
      "linking_domain": "menonimus.org",
      "host_count": "2",
      "edge_count": "1"
    },
    {
      "linking_domain": "meritbatch.com",
      "host_count": "2",
      "edge_count": "1"
    },
    {
      "linking_domain": "msomibora.com",
      "host_count": "2",
      "edge_count": "1"
    },
    {
      "linking_domain": "ncertbooks.guru",
      "host_count": "2",
      "edge_count": "1"
    },
    {
      "linking_domain": "ncertmcq.com",
      "host_count": "2",
      "edge_count": "1"
    },
    {
      "linking_domain": "rbsesolutions.com",
      "host_count": "2",
      "edge_count": "1"
    },
    {
      "linking_domain": "touchheights.com",
      "host_count": "2",
      "edge_count": "1"
    },
    {
      "linking_domain": "upboardguide.com",
      "host_count": "2",
      "edge_count": "1"
    },
    {
      "linking_domain": "upboardsolutions.com",
      "host_count": "2",
      "edge_count": "1"
    },
    {
      "linking_domain": "warstek.com",
      "host_count": "2",
      "edge_count": "1"
    },
    {
      "linking_domain": "artovrag.com",
      "host_count": "1",
      "edge_count": "1"
    },
    {
      "linking_domain": "asseptgel.com.br",
      "host_count": "1",
      "edge_count": "1"
    },
    {
      "linking_domain": "biharboardsolutions.com",
      "host_count": "1",
      "edge_count": "1"
    },
    {
      "linking_domain": "cbsetuts.com",
      "host_count": "1",
      "edge_count": "1"
    },
    {
      "linking_domain": "customerinformation.in",
      "host_count": "1",
      "edge_count": "1"
    },
    {
      "linking_domain": "englishgrammarnotes.com",
      "host_count": "1",
      "edge_count": "1"
    },
    {
      "linking_domain": "gsebsolutions.com",
      "host_count": "1",
      "edge_count": "1"
    },
    {
      "linking_domain": "hkessvpdc.in",
      "host_count": "1",
      "edge_count": "1"
    },
    {
      "linking_domain": "hulkutrischool.in",
      "host_count": "1",
      "edge_count": "1"
    },
    {
      "linking_domain": "iaegerfootball.com",
      "host_count": "1",
      "edge_count": "1"
    },
    {
      "linking_domain": "mcq-questions.com",
      "host_count": "1",
      "edge_count": "1"
    },
    {
      "linking_domain": "mcqmojo.com",
      "host_count": "1",
      "edge_count": "1"
    },
    {
      "linking_domain": "mlaggarwalsolutions.com",
      "host_count": "1",
      "edge_count": "1"
    },
    {
      "linking_domain": "mpboardsolutions.com",
      "host_count": "1",
      "edge_count": "1"
    },
    {
      "linking_domain": "ncert-books.com",
      "host_count": "1",
      "edge_count": "1"
    },
    {
      "linking_domain": "ncert-solution.in",
      "host_count": "1",
      "edge_count": "1"
    },
    {
      "linking_domain": "ncert-solutions.guru",
      "host_count": "1",
      "edge_count": "1"
    },
    {
      "linking_domain": "ncertlibrary.com",
      "host_count": "1",
      "edge_count": "1"
    },
    {
      "linking_domain": "ncertsolutions.guru",
      "host_count": "1",
      "edge_count": "1"
    },
    {
      "linking_domain": "overallscience.com",
      "host_count": "1",
      "edge_count": "1"
    },
    {
      "linking_domain": "ucalybooks.com",
      "host_count": "1",
      "edge_count": "1"
    },
    {
      "linking_domain": "worksheetsbuddy.com",
      "host_count": "1",
      "edge_count": "1"
    }
  ]
}
